ixnetwork_open_traffic_generator/__init__.py
ixnetwork_open_traffic_generator/customfield.py
ixnetwork_open_traffic_generator/ixnetworkapi.py
ixnetwork_open_traffic_generator/lag.py
ixnetwork_open_traffic_generator/ngpf.py
ixnetwork_open_traffic_generator/serdes.py
ixnetwork_open_traffic_generator/timer.py
ixnetwork_open_traffic_generator/trafficitem.py
ixnetwork_open_traffic_generator/validation.py
ixnetwork_open_traffic_generator/vport.py
ixnetwork_open_traffic_generator/docs/openapi.yaml
ixnetwork_open_traffic_generator-0.0.85.dist-info/LICENSE
ixnetwork_open_traffic_generator-0.0.85.dist-info/METADATA
ixnetwork_open_traffic_generator-0.0.85.dist-info/WHEEL
ixnetwork_open_traffic_generator-0.0.85.dist-info/top_level.txt
ixnetwork_open_traffic_generator-0.0.85.dist-info/RECORD
