Metadata-Version: 2.1
Name: ixnetwork-open-traffic-generator
Version: 0.0.85
Summary: The IxNetwork Open Traffic Generator Python Package
Home-page: https://github.com/open-traffic-generator
Author: ajbalogh
Author-email: andy.balogh@keysight.com
License: MIT
Keywords: ixnetwork testing open traffic generator automation
Platform: UNKNOWN
Classifier: Development Status :: 3 - Alpha
Classifier: Intended Audience :: Developers
Classifier: Topic :: Software Development :: Testing :: Traffic Generation
Classifier: License :: OSI Approved :: MIT License
Classifier: Programming Language :: Python :: 2.7
Classifier: Programming Language :: Python :: 3
Requires-Python: >=2.7, <4
License-File: LICENSE
Requires-Dist: pyaml
Requires-Dist: jsonpath-ng
Requires-Dist: abstract-open-traffic-generator (==0.0.69)
Requires-Dist: ixnetwork-restpy (>=1.0.52)
Provides-Extra: dev
Requires-Dist: pytest ; extra == 'dev'
Requires-Dist: flake8 (==3.8.4) ; extra == 'dev'
Requires-Dist: dpkt (==1.9.4) ; extra == 'dev'
